teledex/__init__.py
teledex/main.py
teledex/handlers/__init__.py
teledex/handlers/mujoco.py
teledex-0.0.5.dist-info/METADATA
teledex-0.0.5.dist-info/WHEEL
teledex-0.0.5.dist-info/top_level.txt
teledex-0.0.5.dist-info/RECORD
