Metadata-Version: 2.4
Name: teledex
Version: 0.0.5
Summary: Phone-based Dexterous Robots teleoperation library
Author-email: Omar Rayyan <olr7742@nyu.edu>
License: MIT
Project-URL: Repository, https://github.com/omarrayyann/teledex
Keywords: robotics,teleoperation,ar,ios
Requires-Python: >=3.8
Requires-Dist: numpy
Requires-Dist: scipy
Requires-Dist: websockets
Requires-Dist: qrcode
Requires-Dist: mujoco
Dynamic: requires-python
